PySoly/__init__.py
PySoly/display/__init__.py
PySoly/display/addresses.py
PySoly/display/coordinates.py
pysoly-0.0.1.dist-info/METADATA
pysoly-0.0.1.dist-info/WHEEL
pysoly-0.0.1.dist-info/top_level.txt
pysoly-0.0.1.dist-info/RECORD
