Metadata-Version: 2.4
Name: pysoly
Version: 0.0.1
Summary: The program is designed for convenient interaction with a Windows computer display. The following methods are available: click, get_value, get_int (address), ...
Author: zxc_send
Author-email: karimar.goscha@gmail.com
Keywords: get click
Classifier: Programming Language :: Python :: 3.11
Classifier: License :: OSI Approved :: MIT License
Classifier: Operating System :: Microsoft :: Windows
Requires-Python: >=3.6
Requires-Dist: numpy>=1.25.0
Requires-Dist: pillow>=10.0.0
Requires-Dist: pymem>=1.9.0
Requires-Dist: pywin32>=305
Dynamic: author
Dynamic: author-email
Dynamic: classifier
Dynamic: description
Dynamic: description-content-type
Dynamic: keywords
Dynamic: requires-dist
Dynamic: requires-python
Dynamic: summary
